cqkit/__init__.py
cqkit/cq_basic.py
cqkit/cq_discrete.py
cqkit/cq_fasteners.py
cqkit/cq_files.py
cqkit/cq_geometry.py
cqkit/cq_helpers.py
cqkit/cq_layout.py
cqkit/cq_pprint.py
cqkit/cq_ribbon.py
cqkit/cq_selectors.py
cqkit/cq_xsection.py
cqkit/refdim.py
cqkit-0.5.8.dist-info/LICENSE
cqkit-0.5.8.dist-info/METADATA
cqkit-0.5.8.dist-info/WHEEL
cqkit-0.5.8.dist-info/top_level.txt
cqkit-0.5.8.dist-info/RECORD
